ShixiShenmingShouce/Dockerfile
ShixiShenmingShouce/README.md
ShixiShenmingShouce/__init__.py
ShixiShenmingShouce/__main__.py
ShixiShenmingShouce/file.epub
ShixiShenmingShouce/index.html
ShixiShenmingShouce/css/__init__.py
ShixiShenmingShouce/css/annotations.css
ShixiShenmingShouce/css/main.css
ShixiShenmingShouce/css/normalize.css
ShixiShenmingShouce/css/popup.css
ShixiShenmingShouce/font/__init__.py
ShixiShenmingShouce/font/fontello.eot
ShixiShenmingShouce/font/fontello.svg
ShixiShenmingShouce/font/fontello.ttf
ShixiShenmingShouce/font/fontello.woff
ShixiShenmingShouce/img/__init__.py
ShixiShenmingShouce/img/annotator-glyph-sprite.png
ShixiShenmingShouce/img/annotator-icon-sprite.png
ShixiShenmingShouce/img/apple-touch-icon.png
ShixiShenmingShouce/img/cancelfullscreen.png
ShixiShenmingShouce/img/close.png
ShixiShenmingShouce/img/fullscreen.png
ShixiShenmingShouce/img/loader.gif
ShixiShenmingShouce/img/menu-icon.png
ShixiShenmingShouce/img/save.png
ShixiShenmingShouce/img/saved.png
ShixiShenmingShouce/img/settings-s.png
ShixiShenmingShouce/img/settings.png
ShixiShenmingShouce/img/star.png
ShixiShenmingShouce/js/__init__.py
ShixiShenmingShouce/js/epub.js
ShixiShenmingShouce/js/epub.min.js
ShixiShenmingShouce/js/epub.min.map
ShixiShenmingShouce/js/hooks.min.js
ShixiShenmingShouce/js/hooks.min.map
ShixiShenmingShouce/js/reader.js
ShixiShenmingShouce/js/reader.js.map
ShixiShenmingShouce/js/reader.min.js
ShixiShenmingShouce/js/reader.min.map
ShixiShenmingShouce/js/hooks/__init__.py
ShixiShenmingShouce/js/hooks/extensions/__init__.py
ShixiShenmingShouce/js/hooks/extensions/highlight.js
ShixiShenmingShouce/js/libs/__init__.py
ShixiShenmingShouce/js/libs/jquery.min.js
ShixiShenmingShouce/js/libs/localforage.min.js
ShixiShenmingShouce/js/libs/screenfull.js
ShixiShenmingShouce/js/libs/screenfull.min.js
ShixiShenmingShouce/js/libs/zip.min.js
ShixiShenmingShouce/js/plugins/__init__.py
ShixiShenmingShouce/js/plugins/hypothesis.js
ShixiShenmingShouce/js/plugins/search.js
shixi_shenming_shouce-2022.10.9.1.dist-info/METADATA
shixi_shenming_shouce-2022.10.9.1.dist-info/WHEEL
shixi_shenming_shouce-2022.10.9.1.dist-info/entry_points.txt
shixi_shenming_shouce-2022.10.9.1.dist-info/top_level.txt
shixi_shenming_shouce-2022.10.9.1.dist-info/RECORD
